a_pandas_ex_melt_pivot_tools/LICENSE
a_pandas_ex_melt_pivot_tools/README.MD
a_pandas_ex_melt_pivot_tools/__init__.py
a_pandas_ex_melt_pivot_tools/requirements.txt
a_pandas_ex_melt_pivot_tools/thirdparty.json
a_pandas_ex_melt_pivot_tools-0.10.dist-info/LICENSE.rst
a_pandas_ex_melt_pivot_tools-0.10.dist-info/METADATA
a_pandas_ex_melt_pivot_tools-0.10.dist-info/WHEEL
a_pandas_ex_melt_pivot_tools-0.10.dist-info/top_level.txt
a_pandas_ex_melt_pivot_tools-0.10.dist-info/RECORD
