Metadata-Version: 2.1
Name: a-pandas-ex-melt-pivot-tools
Version: 0.10
Summary: Some useful melt / pivot stuff for pandas DataFrames
Home-page: https://github.com/hansalemaos/a_pandas_ex_melt_pivot_tools
Author: Johannes Fischer
Author-email: <aulasparticularesdealemaosp@gmail.com>
License: MIT
Keywords: pandas,dataframe,melt,pivot
Classifier: Development Status :: 4 - Beta
Classifier: Programming Language :: Python :: 3 :: Only
Classifier: Programming Language :: Python :: 3.9
Classifier: Topic :: Scientific/Engineering :: Visualization
Classifier: Topic :: Software Development :: Libraries :: Python Modules
Classifier: Topic :: Text Editors :: Text Processing
Classifier: Topic :: Text Processing :: General
Classifier: Topic :: Text Processing :: Indexing
Classifier: Topic :: Text Processing :: Filters
Classifier: Topic :: Utilities
License-File: LICENSE.rst
Requires-Dist: pandas
